{
	"description": "项目配置文件。",
	"setting": {
		"urlCheck": false,
		"es6": true,
		"postcss": false,
		"minified": true,
		"newFeature": true
	},
	"compileType": "miniprogram",
	"libVersion": "1.5.2",
	"appid": "wx46966fd292b7eefe",
	"projectname": "wxdc",
	"condition": {
		"search": {
			"current": -1,
			"list": []
		},
		"conversation": {
			"current": -1,
			"list": []
		},
		"plugin": {
			"current": -1,
			"list": []
		},
		"game": {
			"list": []
		},
		"miniprogram": {
			"current": 8,
			"list": [
				{
					"id": -1,
					"name": "列表",
					"pathName": "pages/list/list",
					"query": ""
				},
				{
					"id": -1,
					"name": "订单详情",
					"pathName": "pages/order/balance/balance",
					"query": ""
				},
				{
					"id": 2,
					"name": "我的",
					"pathName": "pages/mine/mine",
					"query": ""
				},
				{
					"id": -1,
					"name": "订单列表",
					"pathName": "pages/order/list/list",
					"query": ""
				},
				{
					"id": 4,
					"name": "订单详情",
					"pathName": "pages/order/detail/detail",
					"query": "dining_id=23"
				},
				{
					"id": -1,
					"name": "订单列表查询窗口",
					"pathName": "pages/order/list/list",
					"query": ""
				},
				{
					"id": -1,
					"name": "我的优惠券",
					"pathName": "pages/coupon/coupon",
					"query": ""
				},
				{
					"id": -1,
					"name": "我的会员卡",
					"pathName": "pages/usercard/usercard",
					"query": ""
				},
				{
					"id": 8,
					"name": "预约号码",
					"pathName": "pages/reserve/reserve",
					"query": "waitNo=234"
				}
			]
		}
	}
}